__init__.py
gotrackit/GlobalVal.py
gotrackit/MapMatch.py
gotrackit/MatchResAna.py
gotrackit/WrapsFunc.py
gotrackit/__init__.py
gotrackit/visualization.py
gotrackit/generation/GpsGen.py
gotrackit/generation/SampleTrip.py
gotrackit/generation/__init__.py
gotrackit/gps/GpsArray.py
gotrackit/gps/GpsTrip.py
gotrackit/gps/GpsXfer.py
gotrackit/gps/LocGps.py
gotrackit/gps/Trajectory.py
gotrackit/gps/__init__.py
gotrackit/log/__init__.py
gotrackit/log/log.py
gotrackit/map/Link.py
gotrackit/map/Net.py
gotrackit/map/Node.py
gotrackit/map/__init__.py
gotrackit/model/Markov.py
gotrackit/model/Para.py
gotrackit/model/__init__.py
gotrackit/netreverse/GlobalVal.py
gotrackit/netreverse/NetGen.py
gotrackit/netreverse/__init__.py
gotrackit/netreverse/book_mark.py
gotrackit/netreverse/format_od.py
gotrackit/netreverse/Parse/__init__.py
gotrackit/netreverse/Parse/gd_car_path.py
gotrackit/netreverse/PublicTools/GeoProcess.py
gotrackit/netreverse/PublicTools/GraphAna.py
gotrackit/netreverse/PublicTools/IndexAna.py
gotrackit/netreverse/PublicTools/MapProcess.py
gotrackit/netreverse/PublicTools/__init__.py
gotrackit/netreverse/PublicTools/od.py
gotrackit/netreverse/Request/__init__.py
gotrackit/netreverse/Request/request_path.py
gotrackit/netreverse/Request/api/WebApi.py
gotrackit/netreverse/Request/api/__init__.py
gotrackit/netreverse/Request/usage/__init__.py
gotrackit/netreverse/Request/usage/bd_ts.py
gotrackit/netreverse/Request/usage/gd_car_path.py
gotrackit/netreverse/RoadNet/__init__.py
gotrackit/netreverse/RoadNet/conn.py
gotrackit/netreverse/RoadNet/increment.py
gotrackit/netreverse/RoadNet/net_reverse.py
gotrackit/netreverse/RoadNet/optimize_net.py
gotrackit/netreverse/RoadNet/save_file.py
gotrackit/netreverse/RoadNet/DupProcess/DupLinks.py
gotrackit/netreverse/RoadNet/DupProcess/__init__.py
gotrackit/netreverse/RoadNet/Merge/__init__.py
gotrackit/netreverse/RoadNet/Merge/get_merged_link_seq.py
gotrackit/netreverse/RoadNet/Merge/merge_links.py
gotrackit-0.3.21.dist-info/licenses/LICENSE
gotrackit-0.3.21.dist-info/METADATA
gotrackit-0.3.21.dist-info/WHEEL
gotrackit-0.3.21.dist-info/top_level.txt
gotrackit-0.3.21.dist-info/RECORD
