Metadata-Version: 2.4
Name: gotrackit
Version: 0.3.21
Summary: A Python Package for Map Matching Algorithm Based on Hidden Markov Model
Author-email: Kai Tang <794568794@qq.com>
License-Expression: MIT
Project-URL: Homepage, https://github.com/zdsjjtTLG/TrackIt
Project-URL: Documentation, https://gotrackit.readthedocs.io/en/latest/index.html
Keywords: HMM,MapMatching,Net,Link,Node,Hidden Markov Model,Algorithm
Classifier: Intended Audience :: Developers
Classifier: Topic :: Software Development :: Build Tools
Classifier: Programming Language :: Python :: 3.9
Classifier: Programming Language :: Python :: 3.10
Classifier: Programming Language :: Python :: 3.11
Classifier: Programming Language :: Python :: 3.12
Classifier: Programming Language :: Python :: 3.13
Requires-Python: >=3.9
License-File: LICENSE
Requires-Dist: geopandas>=0.14.1
Requires-Dist: shapely
Requires-Dist: networkx
Requires-Dist: pandas
Requires-Dist: numpy
Requires-Dist: keplergl
Requires-Dist: geopy
Requires-Dist: tqdm
Requires-Dist: pykalman
Dynamic: license-file
